intecomm_ae/__init__.py
intecomm_ae/action_items.py
intecomm_ae/admin_site.py
intecomm_ae/apps.py
intecomm_ae/baker_recipes.py
intecomm_ae/choices.py
intecomm_ae/constants.py
intecomm_ae/list_data.py
intecomm_ae/urls.py
intecomm_ae/admin/__init__.py
intecomm_ae/admin/ae_followup_admin.py
intecomm_ae/admin/ae_initial_admin.py
intecomm_ae/admin/death_report_admin.py
intecomm_ae/admin/hospitalization_admin.py
intecomm_ae/forms/__init__.py
intecomm_ae/forms/ae_followup_form.py
intecomm_ae/forms/ae_initial_form.py
intecomm_ae/forms/death_report_form.py
intecomm_ae/forms/hospitalization_form.py
intecomm_ae/forms/modelform_mixins.py
intecomm_ae/migrations/0001_initial.py
intecomm_ae/migrations/0002_rename_narrative_aetmg_investigator_narrative_and_more.py
intecomm_ae/migrations/0003_alter_deathreporttmg_cause_of_death_agreed_and_more.py
intecomm_ae/migrations/0004_alter_aefollowup_options_alter_aeinitial_options_and_more.py
intecomm_ae/migrations/0005_alter_aefollowup_managers_alter_aeinitial_managers_and_more.py
intecomm_ae/migrations/0006_hospitalization_historicalhospitalization.py
intecomm_ae/migrations/0007_aeinitial_ae_classification_as_text_and_more.py
intecomm_ae/migrations/0008_alter_deathreporttmgsecond_options_and_more.py
intecomm_ae/migrations/0009_alter_aefollowup_device_created_and_more.py
intecomm_ae/migrations/0010_alter_deathreport_death_date_and_more.py
intecomm_ae/migrations/0011_alter_aefollowup_options_alter_aeinitial_options_and_more.py
intecomm_ae/migrations/0012_aefollowup_intecomm_ae_subject_a0869e_idx_and_more.py
intecomm_ae/migrations/0013_aetmg_intecomm_ae_subject_a182a3_idx_and_more.py
intecomm_ae/migrations/0014_alter_aefollowup_site_alter_aeinitial_site_and_more.py
intecomm_ae/migrations/__init__.py
intecomm_ae/model_mixins/__init__.py
intecomm_ae/model_mixins/ae_review_model_mixin.py
intecomm_ae/models/__init__.py
intecomm_ae/models/ae_followup.py
intecomm_ae/models/ae_initial.py
intecomm_ae/models/compatability.py
intecomm_edc-1.0.1.dist-info/AUTHORS
intecomm_edc-1.0.1.dist-info/LICENSE
intecomm_edc-1.0.1.dist-info/METADATA
intecomm_edc-1.0.1.dist-info/WHEEL
intecomm_edc-1.0.1.dist-info/top_level.txt
intecomm_edc-1.0.1.dist-info/RECORD
