Metadata-Version: 2.2
Name: intecomm-edc
Version: 1.0.1
Summary: INTECOMM Trial EDC (http://www.isrctn.com/ISRCTN76157257)
Home-page: https://github.com/intecomm-trial/intecomm-edc
Author: Erik van Widenfelt
Author-email: ew2789@gmail.com
License: GPL license, see LICENSE
Keywords: django edc INTECOMM EDC,clinicedc,clinical trials
Classifier: Environment :: Web Environment
Classifier: Framework :: Django
Classifier: Framework :: Django :: 5.1
Classifier: Intended Audience :: Developers
Classifier: Intended Audience :: Science/Research
Classifier: Operating System :: OS Independent
Classifier: Programming Language :: Python :: 3.12
Classifier: License :: OSI Approved :: GNU General Public License v3 (GPLv3)
Requires-Python: >=3.12
License-File: LICENSE
License-File: AUTHORS
Requires-Dist: edc==1.0.9
Requires-Dist: beautifulsoup4
Requires-Dist: intecomm-eligibility
Requires-Dist: intecomm-form-validators
Requires-Dist: intecomm-rando
Requires-Dist: edc-next-appointment
Requires-Dist: edc_microscopy
